{"authors.": {"authors": ["Alvaro del Castillo", "Daniel Izquierdo", "Carlos Garcia Campos", "Luis Ca\u00f1as-D\u00edaz", "Jesus M. Gonzalez-Barahona", "Santiago Due\u00f1as", "Israel Herraiz", "Owl Bot", "Luis Ca\u00f1as", "Germ\u00e1n Poo-Caama\u00f1o"], "commits": [3827, 640, 348, 340, 309, 274, 133, 129, 102, 71], "id": [21, 23, 8, 9, 10, 5, 3, 22, 2, 11]}, "authors.last month": {"authors": ["Alvaro del Castillo", "Daniel Izquierdo", "Luis Ca\u00f1as-D\u00edaz", "Santiago Due\u00f1as", "Andy Grunwald", "Jesus M. Gonzalez-Barahona", "Owl Bot", "Zhongpeng Lin (\u6797\u4e2d\u9e4f)"], "commits": [181, 77, 73, 22, 5, 5, 4, 3], "id": [21, 23, 9, 5, 37, 10, 22, 38]}, "authors.last year": {"authors": ["Alvaro del Castillo", "Daniel Izquierdo", "Luis Ca\u00f1as-D\u00edaz", "Santiago Due\u00f1as", "Jesus M. Gonzalez-Barahona", "Owl Bot", "Sumana Harihareswara", "Andy Grunwald", "Germ\u00e1n Poo-Caama\u00f1o", "softmarina"], "commits": [2364, 521, 289, 215, 146, 129, 58, 44, 21, 13], "id": [21, 23, 9, 5, 10, 22, 49, 37, 11, 28]}}