{"diff_netcommits_365":2923,"percentage_commits_365":503,"commits":4848,"first_date":"2006-07-08","last_date":"2013-11-26","committers":31,"authors":38,"files":37857,"branches":22,"repositories":14,"actions":70865,"added_lines":1346303,"removed_lines":1171038,"avg_commits_month":55.0909,"avg_files_month":430.1932,"avg_commits_author":127.5789,"avg_files_author":996.2368,"url":"https://github.com/VizGrimoire/VizGrimoireR.git","type":"git","commits_7":40,"authors_7":5,"files_7":24,"added_lines_7":1109,"removed_lines_7":242,"commits_14":108,"authors_14":7,"files_14":112,"added_lines_14":5323,"removed_lines_14":5109,"commits_30":217,"authors_30":7,"files_30":166,"added_lines_30":12060,"removed_lines_30":7705,"commits_60":494,"authors_60":10,"files_60":6767,"added_lines_60":29806,"removed_lines_60":21716,"commits_90":691,"authors_90":12,"files_90":7148,"added_lines_90":41032,"removed_lines_90":27135,"commits_180":1687,"authors_180":15,"files_180":25381,"added_lines_180":172503,"removed_lines_180":370936,"commits_365":3749,"authors_365":19,"files_365":37174,"added_lines_365":1054860,"removed_lines_365":1017717,"commits_730":4346,"authors_730":24,"files_730":37352,"added_lines_730":1236174,"removed_lines_730":1087814,"core":4,"regular":6,"occasional":28,"diff_netcommits_30":-64,"percentage_commits_30":25,"diff_netcommits_7":-34,"percentage_commits_7":50,"diff_netauthors_365":8,"percentage_authors_365":72,"diff_netauthors_30":-3,"percentage_authors_30":30,"diff_netauthors_7":-2,"percentage_authors_7":28}