{"authors.":{"id":[1,4,20,5,2,16,8,12,54,28],"authors":["Alvaro del Castillo","Daniel Izquierdo Cortazar","Carlos Garcia Campos","Luis Ca\u00f1as-D\u00edaz","Jesus M. Gonzalez-Barahona","Israel Herraiz","Owl Bot","Santiago Due\u00f1as","Sumana Harihareswara","Germ\u00e1n P\u00f3o-Caama\u00f1o"],"commits":[3370,566,348,342,291,133,126,119,58,53]},"authors.last year":{"id":[1,4,5,2,8,12,54,35,7,11],"authors":["Alvaro del Castillo","Daniel Izquierdo Cortazar","Luis Ca\u00f1as-D\u00edaz","Jesus M. Gonzalez-Barahona","Owl Bot","Santiago Due\u00f1as","Sumana Harihareswara","Andy Grunwald","softmarina","tthebosss"],"commits":[2479,512,213,146,126,62,58,32,13,4]},"authors.last month":{"id":[1,4,2,12,5,8,58],"authors":["Alvaro del Castillo","Daniel Izquierdo Cortazar","Jesus M. Gonzalez-Barahona","Santiago Due\u00f1as","Luis Ca\u00f1as-D\u00edaz","Owl Bot","www-data"],"commits":[222,50,45,23,19,14,1]}}