{"actions": 90864, "added_lines": 1868034.0, "added_lines_30": 1111, "added_lines_365": 394748, "added_lines_7": 0, "authors": 47, "authors_30": 2, "authors_365": 22, "authors_7": 0, "avg_commits_author": 166.0435, "avg_commits_month": 79.5625, "avg_files_author": 858.1739, "avg_files_month": 411.2083, "branches": 26, "commits": 6832, "commits_30": 29, "commits_365": 3382, "commits_7": 0, "committers": 47, "companies": 3, "core": 4, "diff_netadded_lines_30": -16269, "diff_netadded_lines_365": -873100, "diff_netadded_lines_7": 0, "diff_netauthors_30": -5, "diff_netauthors_365": 3, "diff_netauthors_7": 0, "diff_netcommits_30": -302, "diff_netcommits_365": 866, "diff_netcommits_7": 0, "diff_netfiles_30": -3573, "diff_netfiles_365": -8419, "diff_netfiles_7": 0, "diff_netremoved_lines_30": -13318, "diff_netremoved_lines_365": -517041, "diff_netremoved_lines_7": 0, "files": 39476, "files_30": 42, "files_365": 17713, "files_7": 0, "first_date": "2006-07-08", "last_date": "2014-08-04", "occasional": 36, "percentage_added_lines_30": 93, "percentage_added_lines_365": 68, "percentage_added_lines_7": 0, "percentage_authors_30": 71, "percentage_authors_365": 15, "percentage_authors_7": 0, "percentage_commits_30": 91, "percentage_commits_365": 34, "percentage_commits_7": 0, "percentage_files_30": 98, "percentage_files_365": 32, "percentage_files_7": 0, "percentage_removed_lines_30": 89, "percentage_removed_lines_365": 48, "percentage_removed_lines_7": 0, "regular": 6, "removed_lines": 1687216.0, "removed_lines_30": 1578, "removed_lines_365": 542092, "removed_lines_7": 0, "repositories": 16, "type": "git", "url": "https://github.com/MetricsGrimoire/Sibyl.git"}