{"authors.": {"authors": ["Santiago Due\u00f1as", "Alvaro del Castillo", "Luis Ca\u00f1as", "Luis Ca\u00f1as-D\u00edaz", "Sumana Harihareswara", "Daniel Izquierdo Cortazar", "Jos\u00e9 Francisco Gato", "Francisco Rivas", "Daniel Izquierdo", "Jesus M. Gonzalez-Barahona"], "commits": [139, 130, 81, 60, 50, 34, 21, 19, 6, 3], "id": [4, 5, 23, 3, 65, 2, 35, 60, 1, 6]}, "authors.last month": {"authors": [], "commits": [], "id": []}, "authors.last year": {"authors": ["Santiago Due\u00f1as", "Alvaro del Castillo", "Daniel Izquierdo"], "commits": [42, 2, 1], "id": [4, 5, 1]}}