{"authors.": {"authors": ["Santiago Due\u00f1as", "Alvaro del Castillo", "Luis Ca\u00f1as", "Luis Ca\u00f1as-D\u00edaz", "Sumana Harihareswara", "Daniel Izquierdo Cortazar", "Juan Francisco Gato Luis", "Francisco Rivas", "Daniel Izquierdo", "Jesus M. Gonzalez-Barahona"], "commits": [154, 141, 81, 60, 50, 27, 21, 19, 13, 3], "id": [9, 6, 5, 8, 73, 24, 18, 68, 13, 4]}, "authors.last month": {"authors": ["Alvaro del Castillo", "Santiago Due\u00f1as"], "commits": [5, 4], "id": [6, 9]}, "authors.last year": {"authors": ["Santiago Due\u00f1as", "Alvaro del Castillo", "Daniel Izquierdo"], "commits": [57, 13, 1], "id": [9, 6, 13]}}