{"actions": 7252, "added_lines": 214879.0, "added_lines_30": 24066, "added_lines_365": 296622, "added_lines_7": 471, "authors": 12, "authors_30": 2, "authors_365": 8, "authors_7": 2, "avg_commits_author": 255.45, "avg_commits_month": 96.9, "avg_files_author": 142.82, "avg_files_month": 54.17, "branches": 7, "commits": 2810, "commits_30": 110, "commits_365": 1690, "commits_7": 11, "committers": 12, "diff_netadded_lines_30": 19710, "diff_netadded_lines_365": -753909, "diff_netadded_lines_7": -2082, "diff_netauthors_30": -2, "diff_netauthors_365": -2, "diff_netauthors_7": 0, "diff_netcommits_30": 85, "diff_netcommits_365": 655, "diff_netcommits_7": -9, "diff_netfiles_30": 281, "diff_netfiles_365": 1286, "diff_netfiles_7": 44, "diff_netremoved_lines_30": 12225, "diff_netremoved_lines_365": -704172, "diff_netremoved_lines_7": -1222, "files": 1571, "files_30": 324, "files_365": 1457, "files_7": 59, "first_date": "2006-07-08", "last_date": "2015-02-03", "percentage_added_lines_30": 452, "percentage_added_lines_365": 71, "percentage_added_lines_7": 81, "percentage_authors_30": 50, "percentage_authors_365": 19, "percentage_authors_7": 0, "percentage_commits_30": 340, "percentage_commits_365": 63, "percentage_commits_7": 44, "percentage_files_30": 653, "percentage_files_365": 752, "percentage_files_7": 293, "percentage_removed_lines_30": 213, "percentage_removed_lines_365": 67, "percentage_removed_lines_7": 77, "removed_lines": 137680.0, "removed_lines_30": 17941, "removed_lines_365": 341265, "removed_lines_7": 347, "repositories": 1}