{"diff_netsenders_30": 1, "diff_netsenders_365": 14, "diff_netsenders_7": -1, "diff_netsent_30": 315, "diff_netsent_365": 1439, "diff_netsent_7": -135, "first_date": "2014-11-23", "last_date": "2015-07-11", "percentage_senders_30": 20, "percentage_senders_365": 0, "percentage_senders_7": 25, "percentage_sent_30": 93, "percentage_sent_365": 0, "percentage_sent_7": 82, "repositories": 1, "senders": 14, "senders_30": 6, "senders_365": 14, "senders_7": 3, "sent": 1439, "sent_30": 651, "sent_365": 1439, "sent_7": 28}