{"authors.": {"authors": ["Brian Waldon", "Jenkins", "Monty Taylor", "Stuart McLaren", "Flavio Percoco", "Cyril Roelandt", "Dirk Mueller", "Chuck Short", "Dean Troyer", "Andrey Kurilin"], "commits": [90, 53, 23, 14, 10, 9, 9, 7, 6, 5], "id": [61, 2, 1, 157, 118, 882, 56, 23, 1013, 898]}, "authors.last month": {"authors": ["Jenkins", "AmalaBasha", "ChangBo Guo(gcb)", "Matt Riedemann", "Stuart McLaren", "zhiyanl-cn"], "commits": [2, 1, 1, 1, 1, 1], "id": [2, 1318, 311, 328, 157, 171]}, "authors.last year": {"authors": ["Jenkins", "Cyril Roelandt", "Dirk Mueller", "Andrey Kurilin", "Yassine Lamgarchal", "Flavio Percoco", "Mark J. Washenberger", "Chuck Short", "Davanum Srinivas", "Eiich Aikawa"], "commits": [26, 9, 6, 5, 5, 4, 4, 3, 3, 3], "id": [2, 882, 56, 898, 1145, 118, 1617, 23, 80, 361]}}