{"actions": 122, "added_lines": 8298.0, "added_lines_30": 31195, "added_lines_365": 311065, "added_lines_7": 551, "authors": 4, "authors_30": 0, "authors_365": 4, "authors_7": 0, "avg_commits_author": 18.5, "avg_commits_month": 7.4, "avg_files_author": 4.75, "avg_files_month": 1.9, "branches": 2, "commits": 74, "commits_30": 0, "commits_365": 54, "commits_7": 0, "committers": 4, "diff_netadded_lines_30": 21818, "diff_netadded_lines_365": -335345, "diff_netadded_lines_7": -104, "diff_netauthors_30": -2, "diff_netauthors_365": 3, "diff_netauthors_7": 0, "diff_netcommits_30": -10, "diff_netcommits_365": 34, "diff_netcommits_7": 0, "diff_netfiles_30": -5, "diff_netfiles_365": 12, "diff_netfiles_7": 0, "diff_netnewauthors_30": 0, "diff_netnewauthors_365": 0, "diff_netnewauthors_7": 0, "diff_netremoved_lines_30": 22999, "diff_netremoved_lines_365": -876071, "diff_netremoved_lines_7": -166, "files": 19, "files_30": 0, "files_365": 19, "files_7": 0, "first_date": "2006-07-08", "last_date": "2015-03-17", "newauthors": 4, "newauthors_30": 0, "newauthors_365": 0, "newauthors_7": 0, "percentage_added_lines_30": 232, "percentage_added_lines_365": 51, "percentage_added_lines_7": 15, "percentage_authors_30": 100, "percentage_authors_365": 300, "percentage_authors_7": 0, "percentage_commits_30": 100, "percentage_commits_365": 170, "percentage_commits_7": 0, "percentage_files_30": 100, "percentage_files_365": 171, "percentage_files_7": 0, "percentage_newauthors_30": 0, "percentage_newauthors_365": 0, "percentage_newauthors_7": 0, "percentage_removed_lines_30": 644, "percentage_removed_lines_365": 81, "percentage_removed_lines_7": 47, "removed_lines": 2355.0, "removed_lines_30": 26566, "removed_lines_365": 201998, "removed_lines_7": 184, "repositories": 1}