{"actions": 14584, "added_lines": 581289.0, "added_lines_30": 22647, "added_lines_365": 295668, "added_lines_7": 671, "authors": 7, "authors_30": 4, "authors_365": 7, "authors_7": 3, "avg_commits_author": 270.71, "avg_commits_month": 65.34, "avg_files_author": 963.29, "avg_files_month": 232.52, "branches": 8, "commits": 1895, "commits_30": 23, "commits_365": 304, "commits_7": 13, "committers": 7, "diff_netadded_lines_30": 16451, "diff_netadded_lines_365": -753558, "diff_netadded_lines_7": 312, "diff_netauthors_30": 3, "diff_netauthors_365": 3, "diff_netauthors_7": 2, "diff_netcommits_30": 20, "diff_netcommits_365": -575, "diff_netcommits_7": 11, "diff_netfiles_30": 13, "diff_netfiles_365": -5966, "diff_netfiles_7": 7, "diff_netremoved_lines_30": -14247, "diff_netremoved_lines_365": -703767, "diff_netremoved_lines_7": 91, "files": 6743, "files_30": 15, "files_365": 79, "files_7": 9, "first_date": "2006-07-08", "last_date": "2015-02-06", "percentage_added_lines_30": 265, "percentage_added_lines_365": 71, "percentage_added_lines_7": 86, "percentage_authors_30": 300, "percentage_authors_365": 75, "percentage_authors_7": 200, "percentage_commits_30": 666, "percentage_commits_365": 65, "percentage_commits_7": 550, "percentage_files_30": 650, "percentage_files_365": 98, "percentage_files_7": 350, "percentage_removed_lines_30": 74, "percentage_removed_lines_365": 67, "percentage_removed_lines_7": 31, "removed_lines": 274040.0, "removed_lines_30": 4826, "removed_lines_365": 341342, "removed_lines_7": 377, "repositories": 1}