{"actions": 58465, "added_lines": null, "added_lines_30": 14043, "added_lines_365": 60654, "added_lines_7": 11461, "authors": 8, "authors_30": 0, "authors_365": 6, "authors_7": 0, "avg_commits_author": 215.14, "avg_commits_month": 65.48, "avg_files_author": 3800.0, "avg_files_month": 1156.52, "branches": 10, "commits": 1506, "commits_30": 0, "commits_365": 181, "commits_7": 0, "committers": 8, "diff_netadded_lines_30": 13994, "diff_netadded_lines_365": -550605, "diff_netadded_lines_7": 9986, "diff_netauthors_30": 0, "diff_netauthors_365": 0, "diff_netauthors_7": 0, "diff_netcommits_30": 0, "diff_netcommits_365": -833, "diff_netcommits_7": 0, "diff_netfiles_30": 0, "diff_netfiles_365": -17854, "diff_netfiles_7": 0, "diff_netremoved_lines_30": 972, "diff_netremoved_lines_365": -33334, "diff_netremoved_lines_7": -362, "files": 26600, "files_30": 0, "files_365": 4368, "files_7": 0, "first_date": "2006-07-08", "last_date": "2015-01-12", "percentage_added_lines_30": 28559, "percentage_added_lines_365": 90, "percentage_added_lines_7": 677, "percentage_authors_30": 0, "percentage_authors_365": 0, "percentage_authors_7": 0, "percentage_commits_30": 0, "percentage_commits_365": 82, "percentage_commits_7": 0, "percentage_files_30": 0, "percentage_files_365": 80, "percentage_files_7": 0, "percentage_removed_lines_30": 32400, "percentage_removed_lines_365": 17, "percentage_removed_lines_7": 63, "removed_lines": null, "removed_lines_30": 975, "removed_lines_365": 159774, "removed_lines_7": 210, "repositories": 1}