{"authors.": {"authors": ["Alvaro del Castillo San Felix", "Luis Ca\u00f1as", "Daniel Izquierdo Cortazar", "Santiago Due\u00f1as", "Manrique Lo\u0301pez", "albertinisg", "Jesus M. Gonzalez-Barahona"], "commits": [1657, 246, 49, 11, 3, 2, 2], "id": [1, 5, 6, 4, 22, 79, 3]}, "authors.last month": {"authors": ["Luis Ca\u00f1as", "Alvaro del Castillo San Felix", "albertinisg", "Santiago Due\u00f1as"], "commits": [33, 20, 2, 1], "id": [5, 1, 79, 4]}, "authors.last year": {"authors": ["Luis Ca\u00f1as", "Alvaro del Castillo San Felix", "Santiago Due\u00f1as", "Manrique Lo\u0301pez", "albertinisg", "Daniel Izquierdo Cortazar", "Jesus M. Gonzalez-Barahona"], "commits": [221, 89, 5, 3, 2, 2, 2], "id": [5, 1, 4, 22, 79, 6, 3]}}